drhawkeye/CoreConfig.ini
drhawkeye/__init__.py
drhawkeye/checkers.py
drhawkeye/framework.py
drhawkeye/health_check.py
drhawkeye/recipes.ini
drhawkeye-0.2.4.dist-info/DESCRIPTION.rst
drhawkeye-0.2.4.dist-info/METADATA
drhawkeye-0.2.4.dist-info/RECORD
drhawkeye-0.2.4.dist-info/WHEEL
drhawkeye-0.2.4.dist-info/metadata.json
drhawkeye-0.2.4.dist-info/top_level.txt
